{
    "vcs_paramclassrepository": [
        "vcs_paramclassrepository",
        "hEeZs",
        "module",
        1
    ],
    "_vcs_unit__368780407": [
        "_vcs_unit__368780407",
        "xEVEs",
        "module",
        5
    ],
    "std": [
        "std",
        "reYIK",
        "module",
        2
    ],
    "bird_pkg": [
        "bird_pkg",
        "fuy3t",
        "module",
        4
    ],
    "bird_if": [
        "bird_if",
        "wiI9B",
        "module",
        6
    ],
    "top_tb": [
        "top_tb",
        "W0eJz",
        "module",
        7
    ],
    "bird": [
        "bird",
        "UD6bB",
        "module",
        8
    ],
    "...MASTER...": [
        "SIM",
        "amcQw",
        "module",
        3
    ]
}